tno/sdg/tabular/eval/utility_metrics/__init__.py
tno/sdg/tabular/eval/utility_metrics/bivariate_correlations.py
tno/sdg/tabular/eval/utility_metrics/bivariate_distributions.py
tno/sdg/tabular/eval/utility_metrics/distinguishability.py
tno/sdg/tabular/eval/utility_metrics/multivariate_predictions_acc.py
tno/sdg/tabular/eval/utility_metrics/multivariate_predictions_acc_regr.py
tno/sdg/tabular/eval/utility_metrics/py.typed
tno/sdg/tabular/eval/utility_metrics/spiderplot.py
tno/sdg/tabular/eval/utility_metrics/univariate_distributions.py
tno/sdg/tabular/eval/utility_metrics/test/__init__.py
tno/sdg/tabular/eval/utility_metrics/test/test_bivariate_correlations.py
tno/sdg/tabular/eval/utility_metrics/test/test_distinguishability.py
tno/sdg/tabular/eval/utility_metrics/test/test_multivariate_predictions_acc.py
tno/sdg/tabular/eval/utility_metrics/test/test_multivariate_predictions_acc_regr.py
tno/sdg/tabular/eval/utility_metrics/test/test_spiderplot.py
tno/sdg/tabular/eval/utility_metrics/test/test_univariate_distributions.py
tno/sdg/tabular/eval/utility_metrics/test/utils.py
tno.sdg.tabular.eval.utility_metrics-0.4.1.dist-info/LICENSE
tno.sdg.tabular.eval.utility_metrics-0.4.1.dist-info/METADATA
tno.sdg.tabular.eval.utility_metrics-0.4.1.dist-info/WHEEL
tno.sdg.tabular.eval.utility_metrics-0.4.1.dist-info/top_level.txt
tno.sdg.tabular.eval.utility_metrics-0.4.1.dist-info/RECORD
