Metadata-Version: 2.1
Name: tno.sdg.tabular.eval.utility_metrics
Version: 0.4.1
Summary: Utility metrics for tabular data
Author-email: TNO PET Lab <petlab@tno.nl>
Maintainer-email: TNO PET Lab <petlab@tno.nl>
License: Apache License, Version 2.0
Project-URL: Homepage, https://pet.tno.nl/
Project-URL: Documentation, https://docs.pet.tno.nl/sdg/tabular/eval/utility_metrics/0.4.1
Project-URL: Source, https://github.com/TNO-SDG/tabular.eval.utility_metrics
Keywords: TNO,SDG,synthetic data,synthetic data generation,tabular,evaluation,utility
Platform: any
Classifier: License :: OSI Approved :: Apache Software License
Classifier: Programming Language :: Python :: 3
Classifier: Operating System :: OS Independent
Classifier: Intended Audience :: Developers
Classifier: Intended Audience :: Information Technology
Classifier: Intended Audience :: Science/Research
Classifier: Typing :: Typed
Classifier: Topic :: Scientific/Engineering
Requires-Python: >=3.9
License-File: LICENSE
Requires-Dist: matplotlib
Requires-Dist: numpy
Requires-Dist: pandas
Requires-Dist: pandas-stubs
Requires-Dist: plotly
Requires-Dist: scikit-learn
Requires-Dist: seaborn
Requires-Dist: statsmodels
Provides-Extra: tests
Requires-Dist: pytest>=8.1; extra == "tests"
